AUTHORS.rst
CONTRIBUTING.rst
HISTORY.rst
LICENSE
MANIFEST.in
README.rst
pyproject.toml
setup.py
src/hide_my_name/__init__.py
src/python_hide_my_name.egg-info/PKG-INFO
src/python_hide_my_name.egg-info/SOURCES.txt
src/python_hide_my_name.egg-info/dependency_links.txt
src/python_hide_my_name.egg-info/requires.txt
src/python_hide_my_name.egg-info/top_level.txt