Metadata-Version: 2.1
Name: python-hide-my-name
Version: 1.0.0
Summary: Automatic proxy finder and tester!
Author-email: Aria Bagheri <ariab9342@gmail.com>
License: MIT License
Project-URL: Homepage, https://github.com/AriaBagheri/python_hide_my_name
Keywords: python,proxy,hide my name,ip,hide
Classifier: License :: OSI Approved :: MIT License
Classifier: Programming Language :: Python
Classifier: Programming Language :: Python :: 3
Requires-Python: >=3.9
License-File: LICENSE
License-File: AUTHORS.rst
